setup.py
mnd/__init__.py
mnd/dispatch.py
mnd/handler.py
mnd/match.py
mnd.egg-info/PKG-INFO
mnd.egg-info/SOURCES.txt
mnd.egg-info/dependency_links.txt
mnd.egg-info/pbr.json
mnd.egg-info/top_level.txt