Metadata-Version: 1.1
Name: mnd
Version: 0.2.1
Summary: Match python args and dispatch based on their contents.
Home-page: https://github.com/stuaxo/mnd
Author: Stuart Axon
Author-email: stuaxo2@yahoo.com
License: MIT
Keywords: match dispatch
Platform: UNKNOWN
Classifier: Development Status :: 3 - Alpha
Classifier: Intended Audience :: Developers
Classifier: Topic :: Software Development :: Build Tools
Classifier: License :: OSI Approved :: MIT License
Classifier: Programming Language :: Python :: 2.7
Classifier: Programming Language :: Python :: 3.4
